benchmarks/__init__.py
benchmarks/bench.py
benchmarks/benchmarks.py
nr/__init__.py
nr/parsing/__init__.py
nr/parsing/date/__init__.py
nr/parsing/date/duration.py
nr/parsing/date/format.py
nr/parsing/date/format_sets.py
nr/parsing/date/options.py
nr/parsing/date/py.typed
nr.parsing.date-1.0.3.dist-info/LICENSE.txt
nr.parsing.date-1.0.3.dist-info/METADATA
nr.parsing.date-1.0.3.dist-info/WHEEL
nr.parsing.date-1.0.3.dist-info/top_level.txt
nr.parsing.date-1.0.3.dist-info/RECORD
