Metadata-Version: 2.1
Name: nr.parsing.date
Version: 1.0.3
Summary: A fast, regular-expression based library for parsing dates, plus support for ISO 8601 durations.
Home-page: https://github.com/NiklasRosenstein/nr-python
Author: Niklas Rosenstein
Author-email: rosensteinniklas@gmail.com
License: MIT
Platform: UNKNOWN
Requires-Python: >=3.6.0,<4.0.0
Provides-Extra: test
